{"index":23,"rank":0,"name":"monachus-monachus","display":"Mediterranean monk seal","definition":"The Mediterranean monk seal  is a monk seal belonging to the family Phocidae.","description":"<p>Adult Mediterranean monk seals can be any color from dark brown or black to light grey. </p><p>They are usually light gray along the belly.</p><p>Males weigh an average of 320 kilograms and females weigh 300 kilograms, with overall weight ranging from 240 to 400 kilograms.</p><p>The snout is short broad and flat, with very pronounced, long nostrils that face upward, unlike their Hawaiian relative, which tend to have more forward nostrils.</p><p>There are eight pairs of teeth in both jaws.</p><p>The flippers are relatively short, with small slender claws.</p><p>They are thought to live up to 45 years old.</p><p>The habitat of Mediterranean monk seals has changed over the years. </p><p>Until the 20th century, they had been known to congregate, give birth, and seek refuge on open beaches. </p><p>In more recent times, they have left their former habitat and now only use sea caves for these activities. </p><p>Because of these seals' shy nature and sensitivity to human disturbance, they have slowly adapted to try to avoid contact with humans.</p><p>Mediterranean monk seals are diurnal and feed on a variety of fish and mollusks, primarily octopus, squid, and eels, up to 3 kilograms per day. </p><p>They are known to forage at depths up to 250 meters, with an average depth varying between specimens.</p><p>Monk seals prefer hunting in wide-open spaces, enabling them to use their speed more effectively. </p><p>They are successful bottom-feeding hunters; some have even been observed lifting slabs of rock in search of prey.</p><p>Mediterranean monk seal generally have no known predators, although a few reports describe predation by killer whales and sharks.</p><p>Pregnant Mediterranean monk seals typically use inaccessible undersea caves while giving birth.</p><p>The monk seals' pups are about 1 meter long and weigh around 15 to 18 kilograms, their skin being covered by 1.5 centimeters long, dark brown to black hair.</p><p>On their bellies, there is a white stripe, which differs in color and shape between the two sexes.</p><p>This hair is replaced after six to eight weeks by the usual short hair adults carry.</p><p>The Mediterranean monk seal spends most of its time in a limited range; they don't migrate long distances. </p><p>There can be up to 20 individuals in a colony of Mediterranean monk seals. </p><p>On land, the seal is a solitary species.</p><p>In the water, they are very good divers and swimmers. </p><p>They swim so well that they can outmaneuver a shark.</p><p>As of 2015, it is estimated that fewer than 700 individuals survive in three or four isolated sub-populations in the Mediterranean.</p><p>It is believed to be the world's rarest pinniped species.</p>","images":{"contextual":{"path":"atlas/monachus-monachus/contextual.jpg","src":"/media/atlas/aquatic-mammals/monachus-monachus/contextual.jpg","caption":null},"cover":{"path":"atlas/monachus-monachus/cover.png","src":"/media/atlas/aquatic-mammals/monachus-monachus/cover.png","caption":null},"icon":{"path":"atlas/monachus-monachus/icon.jpg","src":"/media/atlas/aquatic-mammals/monachus-monachus/icon.jpg","caption":null}},"lastUpdated":"2020-02-22T12:31:21Z","taxonomy":[{"name":"kingdom","display":"Kingdom","value":"Animalia"},{"name":"phylum","display":"Phylum","value":"Chordata"},{"name":"class","display":"Class","value":"Mammalia"},{"name":"order","display":"Order","value":"Carnivora"},{"name":"family","display":"Family","value":"Phocidae"},{"name":"genus","display":"Genus","value":"Monachus"},{"name":"species","display":"Species","value":"Monachus monachus"}],"aliases":[],"spreading":[{"name":"Mediterranean Sea","area":"ALL","less":null,"lessArea":"ALL"},{"name":"Northwest African Coast","area":"ALL","less":null,"lessArea":"ALL"}],"startDate":null,"endDate":null,"conservation":"EN","sampleTitle":null,"samplePath":null,"waveformPath":null,"waveformSrc":null,"facts":[],"features":[{"name":"lifespan","value":6.3113904E8,"maximum":9.4670856E8,"quantity":"TIME","nameDisplay":"Lifespan","valueDisplay":"20 to 30 years"},{"name":"length","value":2.6,"maximum":null,"quantity":"LENGTH","nameDisplay":"Body Length","valueDisplay":"2.6 m"},{"name":"weight","value":240.0,"maximum":400.0,"quantity":"MASS","nameDisplay":"Weight","valueDisplay":"240 to 400 kg"},{"name":"elevation","value":0.0,"maximum":3.0,"quantity":"LENGTH","nameDisplay":"Elevation","valueDisplay":"Up to 3 m"},{"name":"depth","value":0.0,"maximum":250.0,"quantity":"LENGTH","nameDisplay":"Diving Depth","valueDisplay":"Up to 250 m"},{"name":"lifespan.record","value":1.42006284E9,"maximum":null,"quantity":"TIME","nameDisplay":"Lifespan Record","valueDisplay":"45 years"}],"related":[{"index":30,"display":"South American sea lion","definition":"The South American sea lion is a sea lion found on the coasts of South America.","iconPath":"atlas/otaria-flavescens/icon.jpg","iconSrc":null},{"index":31,"display":"Southern elephant seal","definition":"The southern elephant seal  is one of the two species of elephant seals.","iconPath":"atlas/mirounga-leonina/icon.jpg","iconSrc":null},{"index":22,"display":"Leopard seal","definition":"The leopard seal is the second largest species of seal in the Antarctic.","iconPath":"atlas/hydrurga-leptonyx/icon.jpg","iconSrc":null},{"index":35,"display":"Walrus","definition":"The walrus  is a large flippered marine mammal with a discontinuous distribution about the North Pole in the Arctic Ocean and subarctic seas of the Northern Hemisphere.","iconPath":"atlas/odobenus-rosmarus/icon.jpg","iconSrc":null},{"index":6,"display":"California sea lion","definition":"The California sea lion  is a coastal eared seal native to western North America.","iconPath":"atlas/zalophus-californianus/icon.jpg","iconSrc":null},{"index":9,"display":"Crabeater seal","definition":"The crabeater seal s a true seal with a circumpolar distribution around the coast of Antarctica.","iconPath":"atlas/lobodon-carcinophaga/icon.jpg","iconSrc":null}],"links":[{"url":"https://en.wikipedia.org/wiki/Mediterranean_monk_seal","display":"Wikipedia","description":"Wikipedia article about mediterranean monk seal.","iconPath":"link/wikipedia.png","iconSrc":"/media/link/wikipedia.png"},{"url":"https://www.britannica.com/animal/monk-seal","display":"Encyclopædia Britannica","description":"Monk seals article on Britannica.","iconPath":"link/britannica.png","iconSrc":"/media/link/britannica.png"},{"url":"https://animaldiversity.org/accounts/Monachus_monachus/","display":"Animal Diversity Web","description":"Mediterranean monk seal on Animal Diversity Web.","iconPath":"link/animaldiversity.png","iconSrc":"/media/link/animaldiversity.png"},{"url":"https://www.iucnredlist.org/species/13653/117647375","display":"IUCN Red List","description":"IUCN Red List index of mediterranean monk seal.","iconPath":"link/iucnredlist.png","iconSrc":"/media/link/iucnredlist.png"},{"url":"https://www.itis.gov/servlet/SingleRpt/SingleRpt?search_topic=TSN&search_value=180659#null","display":"Taxonomic Information System","description":"ITIS taxonomy for mediterranean monk seal.","iconPath":"link/itis.png","iconSrc":"/media/link/itis.png"},{"url":"https://eol.org/pages/46559158","display":"Encyclopedia of Life","description":"Data, maps and articles about mediterranean monk seal.","iconPath":"link/eol.png","iconSrc":"/media/link/eol.png"},{"url":"https://www.thefreedictionary.com/monk+seal","display":"The Free Dictionary","description":"Monk seal definition on dictionary.","iconPath":"link/thefreedictionary.png","iconSrc":"/media/link/thefreedictionary.png"}]}